Workbook

Sheet Summary
B1: 94 MARGARET AVE — PRICE TO DRYWALL
B2: Rachel Milisic | rmilisic@hotmail.com | Stoney Creek (Hamilton), ON | New 2-storey detached, entry level | PalmView Contracting Inc. | Oct 21, 2026
C4: ABOVE-GRADE AREA | D4: PRICE TO DRYWALL | E4: WITH HST | F4: GROSS MARGIN | G4: GROSS PROFIT | H4: PRICE / SF
C5: =D12 -> 2930 | D5: =E37 -> 1759497.9 | E5: =E39 -> 1988232.6 | F5: =G11 -> 0.4 | G5: =F35 -> 674999.15 | H5: =E37/D12 -> 600.51122
C6: Main 1,460 + Second 1,470 | D6: before HST | E6: 13% HST included | F6: on PalmView price | G6: to drywall | H6: above grade
C8: HOUSE SIZE | F8: PRICING INPUTS
C9: Main floor | D9: 1460 | F9: HST | G9: 0.13
C10: Second floor | D10: 1470 | F10: Contingency (on hard cost) | G10: 0.05
F11: TARGET GROSS MARGIN | G11: 0.4
C12: TOTAL ABOVE GRADE (finished) | D12: =D9+D10 -> 2930 | F12: Equals markup on cost of | G12: =G11/(1-G11) -> 0.66666667
C13: Basement (unfinished, not in SF) | D13: 1460 | F13: Edit yellow cells; everything updates.
C14: Two-car garage | D14: 548
B16: DIVISION BREAKDOWN — FIXED PRICE TO DRYWALL
B17: # | C17: Division | D17: Cost | E17: Price | F17: Gross Profit | G17: Price / SF | H17: % of Price
B18: 1 | C18: Permits, Engineering & Soft Costs | D18: ='Division Detail'!$H$15 -> 43800 | E18: =D18/(1-$G$11) -> 73000 | F18: =E18-D18 -> 29200 | G18: =E18/$D$12 -> 24.914676 | H18: =E18/$E$37 -> 0.041489109
B19: 2 | C19: Site Supervision & General Conditions | D19: ='Division Detail'!$H$34 -> 134750 | E19: =D19/(1-$G$11) -> 224583.33 | F19: =E19-D19 -> 89833.333 | G19: =E19/$D$12 -> 76.649602 | H19: =E19/$E$37 -> 0.12764058
B20: 3 | C20: Demolition & Site Preparation | D20: ='Division Detail'!$H$40 -> 35600 | E20: =D20/(1-$G$11) -> 59333.333 | F20: =E20-D20 -> 23733.333 | G20: =E20/$D$12 -> 20.250284 | H20: =E20/$E$37 -> 0.033721742
B21: 4 | C21: Excavation, Backfill & Grading | D21: ='Division Detail'!$H$47 -> 35270 | E21: =D21/(1-$G$11) -> 58783.333 | F21: =E21-D21 -> 23513.333 | G21: =E21/$D$12 -> 20.062571 | H21: =E21/$E$37 -> 0.033409153
B22: 5 | C22: Footings, Foundation & Waterproofing | D22: ='Division Detail'!$H$57 -> 93988 | E22: =D22/(1-$G$11) -> 156646.67 | F22: =E22-D22 -> 62658.667 | G22: =E22/$D$12 -> 53.463026 | H22: =E22/$E$37 -> 0.089029188
B23: 6 | C23: Concrete Slabs | D23: ='Division Detail'!$H$63 -> 29904 | E23: =D23/(1-$G$11) -> 49840 | F23: =E23-D23 -> 19936 | G23: =E23/$D$12 -> 17.010239 | H23: =E23/$E$37 -> 0.028326263
B24: 7 | C24: Framing & Structural Steel | D24: ='Division Detail'!$H$71 -> 181384 | E24: =D24/(1-$G$11) -> 302306.67 | F24: =E24-D24 -> 120922.67 | G24: =E24/$D$12 -> 103.17634 | H24: =E24/$E$37 -> 0.17181417
B25: 8 | C25: Roofing, Soffit, Fascia & Eaves | D25: ='Division Detail'!$H$80 -> 43745 | E25: =D25/(1-$G$11) -> 72908.333 | F25: =E25-D25 -> 29163.333 | G25: =E25/$D$12 -> 24.88339 | H25: =E25/$E$37 -> 0.041437011
B26: 9 | C26: Windows & Exterior Doors | D26: ='Division Detail'!$H$89 -> 32984 | E26: =D26/(1-$G$11) -> 54973.333 | F26: =E26-D26 -> 21989.333 | G26: =E26/$D$12 -> 18.76223 | H26: =E26/$E$37 -> 0.031243762
B27: 10 | C27: Exterior Cladding: Brick, Stone & Stucco | D27: ='Division Detail'!$H$96 -> 162940 | E27: =D27/(1-$G$11) -> 271566.67 | F27: =E27-D27 -> 108626.67 | G27: =E27/$D$12 -> 92.684869 | H27: =E27/$E$37 -> 0.15434328
B28: 11 | C28: Plumbing Rough-In | D28: ='Division Detail'!$H$101 -> 26500 | E28: =D28/(1-$G$11) -> 44166.667 | F28: =E28-D28 -> 17666.667 | G28: =E28/$D$12 -> 15.073948 | H28: =E28/$E$37 -> 0.025101858
B29: 12 | C29: HVAC & Gas Rough-In | D29: ='Division Detail'!$H$106 -> 28500 | E29: =D29/(1-$G$11) -> 47500 | F29: =E29-D29 -> 19000 | G29: =E29/$D$12 -> 16.211604 | H29: =E29/$E$37 -> 0.026996338
B30: 13 | C30: Electrical Rough-In & Service | D30: ='Division Detail'!$H$113 -> 33350 | E30: =D30/(1-$G$11) -> 55583.333 | F30: =E30-D30 -> 22233.333 | G30: =E30/$D$12 -> 18.970421 | H30: =E30/$E$37 -> 0.031590452
B31: 14 | C31: Insulation & Air Sealing | D31: ='Division Detail'!$H$120 -> 22127.5 | E31: =D31/(1-$G$11) -> 36879.167 | F31: =E31-D31 -> 14751.667 | G31: =E31/$D$12 -> 12.586746 | H31: =E31/$E$37 -> 0.020960052
B32: 15 | C32: Drywall (Level 4, unprimed) | D32: ='Division Detail'!$H$124 -> 48692 | E32: =D32/(1-$G$11) -> 81153.333 | F32: =E32-D32 -> 32461.333 | G32: =E32/$D$12 -> 27.697383 | H32: =E32/$E$37 -> 0.046123007
B33: 16 | C33: Site Cleanup & Closeout | D33: ='Division Detail'!$H$131 -> 10750 | E33: =D33/(1-$G$11) -> 17916.667 | F33: =E33-D33 -> 7166.6667 | G33: =E33/$D$12 -> 6.1149033 | H33: =E33/$E$37 -> 0.010182829
B34: 17 | C34: Construction Contingency (5% reserve) | D34: =SUM(D18:D33)*G10 -> 48214.225 | E34: =D34/(1-$G$11) -> 80357.042 | F34: =E34-D34 -> 32142.817 | G34: =E34/$D$12 -> 27.425611 | H34: =E34/$E$37 -> 0.04567044
C35: PALMVIEW FIXED PRICE (40% margin) | D35: =SUM(D18:D34) -> 1012498.7 | E35: =SUM(E18:E34) -> 1687497.9 | F35: =E35-D35 -> 674999.15 | G35: =E35/$D$12 -> 575.93784 | H35: =E35/$E$37 -> 0.95907923
C36: Municipal & Utility Fees — permit, DCs, utilities (at cost, no margin) | D36: ='Division Detail'!$H$138 -> 72000 | E36: =D36 -> 72000 | F36: =E36-D36 -> 0 | G36: =E36/$D$12 -> 24.573379 | H36: =E36/$E$37 -> 0.040920766
C37: TOTAL TO DRYWALL (before HST) | D37: =D35+D36 -> 1084498.7 | E37: =E35+E36 -> 1759497.9 | F37: =E37-D37 -> 674999.15 | G37: =E37/$D$12 -> 600.51122 | H37: =E37/$E$37 -> 1
C38: HST 13% | E38: =E37*G9 -> 228734.72
C39: TOTAL INCLUDING HST | E39: =E37+E38 -> 1988232.6
B41: MARGIN CHECK — PALMVIEW SCOPE (EXCLUDES PASS-THROUGH FEES)
C42: PalmView cost (incl. contingency) | D42: =D35 -> 1012498.7 | F42: 40% margin means 40 cents of every dollar the client pays
C43: PalmView price | D43: =E35 -> 1687497.9 | F43: is gross profit. On cost, that is a 66.7% markup.
C44: Gross profit | D44: =E35-D35 -> 674999.15 | F44: PalmView's standard 35% markup would equal a 25.9% margin.
C45: Gross margin (profit ÷ price) | D45: =D44/D43 -> 0.4 | F45: Fees passed through at cost carry no margin.
C46: Markup (profit ÷ cost) | D46: =D44/D42 -> 0.66666667
B48: INCLUDED TO DRYWALL | F48: NOT INCLUDED
B49: ✓ Demolition of existing house and site prep | F49: ✕ Prime coat and paint
B50: ✓ Excavation, foundation, waterproofing, slabs | F50: ✕ Mechanical and electrical finish and startup
B51: ✓ Framing, steel, trusses, roofing | F51: ✕ All interior finishes and fixtures
B52: ✓ Vinyl double-pane windows, steel doors, garage door | F52: ✕ Basement finishing (left unfinished)
B53: ✓ Brick, stone and stucco as drawn | F53: ✕ Driveway, landscaping, final grading
B54: ✓ Plumbing, gas, HVAC and electrical ROUGH-IN only | F54: ✕ Garage door opener, appliances
B55: ✓ Furnace, A/C, HRV supply; 200 A service | F55: ✕ Rock, dewatering, shoring if required
B56: ✓ Insulation, air test, Level 4 drywall (unprimed) | F56: ✕ HST (shown separately)
B58: Confirm before issue: lumber quote, Hamilton development charge credit, foundation wall thickness, abatement after DSS, window count.

Sheet Division Detail
B1: DIVISION DETAIL — FIXED PRICE TO DRYWALL
B2: Every line item behind the Summary. Blue = quantities and unit costs from the PalmView Cost Index; price = cost ÷ (1 − margin).
B4: Code | C4: Cost Item | D4: Scope Description | E4: Qty | F4: Unit | G4: Unit Cost | H4: Cost | I4: Price
B5: PERMITS, ENGINEERING & SOFT COSTS
B6: 1.002 | C6: City Permit Package | D6: City permit package: zoning review, application forms and submission to City of Hamilton. | E6: 1 | F6: Lump Sum | G6: 15000 | H6: =E6*G6 -> 15000 | I6: =H6/(1-Summary!$G$11) -> 25000
B7: 1.029 | C7: Permit Coordination Fee | D7: Permit coordination with City, designer (Bobicon) and AM Engineering through issuance. | E7: 1 | F7: Lump Sum | G7: 3000 | H7: =E7*G7 -> 3000 | I7: =H7/(1-Summary!$G$11) -> 5000
B8: 1.007 | C8: Engineering (Structural, Mechanical & Heat Loss) | D8: Engineering: structural (steel beams, lintels), HVAC design and heat loss / SB-12 EEDS. | E8: 1 | F8: Lump Sum | G8: 7000 | H8: =E8*G8 -> 7000 | I8: =H8/(1-Summary!$G$11) -> 11666.667
B9: 1.070 | C9: Truss Layout Drawings | D9: Truss layout drawings for hip roof and girder trusses. | E9: 1 | F9: Lump Sum | G9: 1500 | H9: =E9*G9 -> 1500 | I9: =H9/(1-Summary!$G$11) -> 2500
B10: 1.030 | C10: Surveyor Stakeout, Footing Pins & Wall Pins | D10: Surveyor stakeout, footing pins and wall pins. | E10: 1 | F10: Lump Sum | G10: 2200 | H10: =E10*G10 -> 2200 | I10: =H10/(1-Summary!$G$11) -> 3666.6667
B11: 1.031 | C11: As-Built Survey / Survey Revisions | D11: As-built / foundation location survey. | E11: 1 | F11: Lump Sum | G11: 1800 | H11: =E11*G11 -> 1800 | I11: =H11/(1-Summary!$G$11) -> 3000
B12: 1.020 | C12: Site Field Reviews by Engineer | D12: AM Engineering site reviews: servicing inspection and lot grading. | E12: 2 | F12: Each | G12: 1800 | H12: =E12*G12 -> 3600 | I12: =H12/(1-Summary!$G$11) -> 6000
B13: 1.067 | C13: Hazardous Substance Report | D13: Designated substance survey of existing house before demolition (O. Reg. 278/05). | E13: 1 | F13: Lump Sum | G13: 1200 | H13: =E13*G13 -> 1200 | I13: =H13/(1-Summary!$G$11) -> 2000
B14: 1.021 | C14: Tarion Warranty Enrollment | D14: Tarion new home warranty enrolment. | E14: 1 | F14: Lump Sum | G14: 8500 | H14: =E14*G14 -> 8500 | I14: =H14/(1-Summary!$G$11) -> 14166.667
C15: Subtotal — Permits, Engineering & Soft Costs | H15: =SUM(H6:H14) -> 43800 | I15: =SUM(I6:I14) -> 73000
B17: SITE SUPERVISION & GENERAL CONDITIONS
B18: 1.036 | C18: Tree Protection | D18: Tree protection hoarding at City boulevard tree per City of Hamilton requirements. | E18: 1 | F18: Lump Sum | G18: 4500 | H18: =E18*G18 -> 4500 | I18: =H18/(1-Summary!$G$11) -> 7500
B19: 1.040 | C19: Site Supervision & Project Management (Blended Monthly) | D19: Site supervision and project management, 6 months demo through drywall. | E19: 6 | F19: Months | G19: 12000 | H19: =E19*G19 -> 72000 | I19: =H19/(1-Summary!$G$11) -> 120000
B20: 1.042 | C20: Temporary Hoarding & Safety Fences | D20: Temporary construction fence, front and sides. | E20: 160 | F20: Linear Feet | G20: 45 | H20: =E20*G20 -> 7200 | I20: =H20/(1-Summary!$G$11) -> 12000
B21: 1.043 | C21: Temporary Toilet | D21: Temporary toilet, 6 months. | E21: 6 | F21: Months | G21: 250 | H21: =E21*G21 -> 1500 | I21: =H21/(1-Summary!$G$11) -> 2500
B22: 1.044 | C22: Temporary Hydro | D22: Temporary hydro service. | E22: 1 | F22: Lump Sum | G22: 3500 | H22: =E22*G22 -> 3500 | I22: =H22/(1-Summary!$G$11) -> 5833.3333
B23: 1.045 | C23: Temporary Water | D23: Temporary water. | E23: 1 | F23: Lump Sum | G23: 2800 | H23: =E23*G23 -> 2800 | I23: =H23/(1-Summary!$G$11) -> 4666.6667
B24: 1.046 | C24: Temporary Heating (Winter) | D24: Temporary heat, winter months (if schedule falls in winter). | E24: 3 | F24: Months | G24: 2200 | H24: =E24*G24 -> 6600 | I24: =H24/(1-Summary!$G$11) -> 11000
B25: 1.047 | C25: Crane Service (incl. Operator & Rigging) | D25: Crane with operator to set roof trusses, 1 day. | E25: 1 | F25: Days | G25: 2800 | H25: =E25*G25 -> 2800 | I25: =H25/(1-Summary!$G$11) -> 4666.6667
B26: 1.050 | C26: Scaffold Rental | D26: Scaffold rental for masonry and stucco, 4 months. | E26: 4 | F26: Months | G26: 1500 | H26: =E26*G26 -> 6000 | I26: =H26/(1-Summary!$G$11) -> 10000
B27: 1.051 | C27: Waste Disposal / Garbage Bins | D27: Waste bins and disposal, 6 months. | E27: 6 | F27: Months | G27: 1800 | H27: =E27*G27 -> 10800 | I27: =H27/(1-Summary!$G$11) -> 18000
B28: 1.052 | C28: Miscellaneous Supplies & Materials | D28: Miscellaneous supplies and materials. | E28: 1 | F28: Lump Sum | G28: 8000 | H28: =E28*G28 -> 8000 | I28: =H28/(1-Summary!$G$11) -> 13333.333
B29: 1.053 | C29: Safety Supplies | D29: Safety supplies, fall protection, first aid. | E29: 1 | F29: Lump Sum | G29: 3500 | H29: =E29*G29 -> 3500 | I29: =H29/(1-Summary!$G$11) -> 5833.3333
... B33: 1.069 | C33: Line Protection / Utility Locates | D33: Utility locates. | E33: 1 | F33: Lump Sum | G33: 900 | H33: =E33*G33 -> 900 | I33: =H33/(1-Summary!$G$11) -> 1500
C34: Subtotal — Site Supervision & General Conditions | H34: =SUM(H18:H33) -> 134750 | I34: =SUM(I18:I33) -> 224583.33
B36: DEMOLITION & SITE PREPARATION
B37: 1.068 | C37: Environmental Abatement | D37: Provisional environmental abatement allowance for existing house (asbestos/vermiculite). | E37: 1 | F37: Lump Sum | G37: 8000 | H37: =E37*G37 -> 8000 | I37: =H37/(1-Summary!$G$11) -> 13333.333
B38: 2.001 | C38: House Demolition | D38: Demolish existing 1-storey dwelling incl. basement, foundations and rear shed; dispose. | E38: 1300 | F38: Square Foot | G38: 12 | H38: =E38*G38 -> 15600 | I38: =H38/(1-Summary!$G$11) -> 26000
B39: 2.003 | C39: Site Clearing | D39: Site clearing of shrubs, vegetation and stumps within the building and work area. | E39: 1 | F39: Lump Sum | G39: 12000 | H39: =E39*G39 -> 12000 | I39: =H39/(1-Summary!$G$11) -> 20000
C40: Subtotal — Demolition & Site Preparation | H40: =SUM(H37:H39) -> 35600 | I40: =SUM(I37:I39) -> 59333.333
B42: EXCAVATION, BACKFILL & GRADING
B43: 2.019 | C43: Excavation & Ground works | D43: Excavate basement (1,460 SF, BFE 98.55) plus overdig and frost wall trenches; incl. haul-away of excess per index scope. | E43: 600 | F43: Cubic Yard | G43: 22 | H43: =E43*G43 -> 13200 | I43: =H43/(1-Summary!$G$11) -> 22000
B44: 2.070 | C44: Backfill | D44: Backfill foundation walls and frost walls. | E44: 190 | F44: Cubic Yard | G44: 28 | H44: =E44*G44 -> 5320 | I44: =H44/(1-Summary!$G$11) -> 8866.6667
B45: 2.073 | C45: Rough Grading | D45: Rough grading around building per AM Engineering grading plan. | E45: 2500 | F45: Square Foot | G45: 5 | H45: =E45*G45 -> 12500 | I45: =H45/(1-Summary!$G$11) -> 20833.333
B46: 2.071 | C46: Service Trenching | D46: Service trenching for new water and sewer laterals to 1.0 m from building face. | E46: 50 | F46: Linear Feet | G46: 85 | H46: =E46*G46 -> 4250 | I46: =H46/(1-Summary!$G$11) -> 7083.3333
C47: Subtotal — Excavation, Backfill & Grading | H47: =SUM(H43:H46) -> 35270 | I47: =SUM(I43:I46) -> 58783.333
B49: FOOTINGS, FOUNDATION & WATERPROOFING
B50: 2.046 | C50: Footings (Forming, Rebar & Concrete) | D50: Strip footings at basement, garage and patio frost walls plus pad footings, all-in. | E50: 314 | F50: Linear Feet | G50: 70 | H50: =E50*G50 -> 21980 | I50: =H50/(1-Summary!$G$11) -> 36633.333
B51: 2.080 | C51: Foundation Walls - Poured In Place (8" formed, 3-bar) | D51: Basement foundation walls incl. cold room, approx. 8'-10" high, all-in. Drawings show 10"/12" walls; confirm thickness. | E51: 181 | F51: Linear Feet | G51: 150 | H51: =E51*G51 -> 27150 | I51: =H51/(1-Summary!$G$11) -> 45250
B52: 2.080 | C52: Foundation Walls - Poured In Place (8" formed, 3-bar) | D52: Garage and rear patio frost walls (unexcavated areas), all-in. | E52: 113 | F52: Linear Feet | G52: 150 | H52: =E52*G52 -> 16950 | I52: =H52/(1-Summary!$G$11) -> 28250
B53: 2.051 | C53: Waterproofing | D53: Bituminous dampproofing and drainage mat on basement walls below grade. | E53: 1360 | F53: Square Foot | G53: 12 | H53: =E53*G53 -> 16320 | I53: =H53/(1-Summary!$G$11) -> 27200
B54: 2.053 | C54: Weeping Tile | D54: Weeping tile at basement footing perimeter to sump. | E54: 181 | F54: Linear Feet | G54: 28 | H54: =E54*G54 -> 5068 | I54: =H54/(1-Summary!$G$11) -> 8446.6667
B55: 2.058 | C55: Perimeter Drainage 3/4" Crush | D55: 3/4" clear stone cover over weeping tile. | E55: 90 | F55: Ton | G55: 48 | H55: =E55*G55 -> 4320 | I55: =H55/(1-Summary!$G$11) -> 7200
B56: 3.105 | C56: Concrete Pump (hardscape) | D56: Concrete pumping, all foundation and slab pours (approx. 100 CY). | E56: 100 | F56: Cubic Yard | G56: 22 | H56: =E56*G56 -> 2200 | I56: =H56/(1-Summary!$G$11) -> 3666.6667
C57: Subtotal — Footings, Foundation & Waterproofing | H57: =SUM(H50:H56) -> 93988 | I57: =SUM(I50:I56) -> 156646.67
B59: CONCRETE SLABS
B60: 2.054 | C60: Basement Slab | D60: Basement slab: 3" 25 MPa on 6" granular, R10 perimeter insulation per slab detail. | E60: 1460 | F60: Square Foot | G60: 12 | H60: =E60*G60 -> 17520 | I60: =H60/(1-Summary!$G$11) -> 29200
B61: 2.054 | C61: Basement Slab | D61: Garage slab on compacted granular. | E61: 548 | F61: Square Foot | G61: 12 | H61: =E61*G61 -> 6576 | I61: =H61/(1-Summary!$G$11) -> 10960
B62: 2.056 | C62: Porch Slabs | D62: Front porch (60 SF) and raised rear covered patio (204 SF) slabs. | E62: 264 | F62: Square Foot | G62: 22 | H62: =E62*G62 -> 5808 | I62: =H62/(1-Summary!$G$11) -> 9680
C63: Subtotal — Concrete Slabs | H63: =SUM(H60:H62) -> 29904 | I63: =SUM(I60:I62) -> 49840
B65: FRAMING & STRUCTURAL STEEL
B66: 3.002 | C66: Framing Materials | D66: Framing materials: house 2,930 SF + garage 548 SF, incl. floors, walls, roof trusses, flat roofs, sheathing. LIVE LUMBER QUOTE REQUIRED. | E66: 3478 | F66: Square Foot | G66: 20 | H66: =E66*G66 -> 69560 | I66: =H66/(1-Summary!$G$11) -> 115933.33
B67: 3.006 | C67: Framing Labour | D67: Framing labour, same area. | E67: 3478 | F67: Square Foot | G67: 18 | H67: =E67*G67 -> 62604 | I67: =H67/(1-Summary!$G$11) -> 104340
B68: 3.133 | C68: Back Framing - Whole-House Basis (budget stage) | D68: Back framing, whole-house budget basis (blocking, bulkheads, stair framing). | E68: 2930 | F68: Square Foot | G68: 4 | H68: =E68*G68 -> 11720 | I68: =H68/(1-Summary!$G$11) -> 19533.333
B69: 3.009 | C69: Steel Beams | D69: Steel beams: W10x22 x2 (basement), W8x28, W8x31/W10x22, W8x18 x2, W10x26 (garage). | E69: 7 | F69: Each | G69: 4500 | H69: =E69*G69 -> 31500 | I69: =H69/(1-Summary!$G$11) -> 52500
B70: 3.010 | C70: Steel Posts | D70: Steel posts / columns with base plates. | E70: 5 | F70: Each | G70: 1200 | H70: =E70*G70 -> 6000 | I70: =H70/(1-Summary!$G$11) -> 10000
C71: Subtotal — Framing & Structural Steel | H71: =SUM(H66:H70) -> 181384 | I71: =SUM(I66:I70) -> 302306.67
B73: ROOFING, SOFFIT, FASCIA & EAVES
B74: 3.014 | C74: Roofing material & labour (Shingle) | D74: Asphalt shingle hip roof incl. underlayment, ice & water, flashings and roof vents (5/12, approx. 1,850 SF). | E74: 1850 | F74: Square Foot | G74: 8 | H74: =E74*G74 -> 14800 | I74: =H74/(1-Summary!$G$11) -> 24666.667
B75: 3.015 | C75: Torch on install and supply (Flat Roof) | D75: Torch-on flat roof membrane over garage, front porch, rear patio and front roof sections, sloped 2% to scuppers. | E75: 950 | F75: Square Foot | G75: 12 | H75: =E75*G75 -> 11400 | I75: =H75/(1-Summary!$G$11) -> 19000
B76: 3.032 | C76: Flashing and aluminum capping | D76: Aluminum parapet capping and flashing at flat roofs. | E76: 165 | F76: Linear Feet | G76: 45 | H76: =E76*G76 -> 7425 | I76: =H76/(1-Summary!$G$11) -> 12375
B77: 3.069 | C77: Soffits | D77: Prefinished aluminum soffit. | E77: 220 | F77: Linear Feet | G77: 16 | H77: =E77*G77 -> 3520 | I77: =H77/(1-Summary!$G$11) -> 5866.6667
B78: 3.070 | C78: Fascia | D78: Prefinished aluminum fascia. | E78: 220 | F78: Linear Feet | G78: 14 | H78: =E78*G78 -> 3080 | I78: =H78/(1-Summary!$G$11) -> 5133.3333
B79: 3.071 | C79: Eavestroughs & Downspouts | D79: Eavestrough and downspouts. | E79: 220 | F79: Linear Feet | G79: 16 | H79: =E79*G79 -> 3520 | I79: =H79/(1-Summary!$G$11) -> 5866.6667
C80: Subtotal — Roofing, Soffit, Fascia & Eaves | H80: =SUM(H74:H79) -> 43745 | I80: =SUM(I74:I79) -> 72908.333
B82: WINDOWS & EXTERIOR DOORS
B83: 3.019 | C83: Windows (Basic vinyl) | D83: Vinyl double-pane low-E windows W1-W8 (14 units, approx. 430 SF), supply and install. | E83: 430 | F83: Square Foot | G83: 42 | H83: =E83*G83 -> 18060 | I83: =H83/(1-Summary!$G$11) -> 30100
B84: 3.019 | C84: Windows (Basic vinyl) | D84: D3 vinyl patio sliding door 8'-0" x 9'-0" with transom, supply and install. | E84: 72 | F84: Square Foot | G84: 42 | H84: =E84*G84 -> 3024 | I84: =H84/(1-Summary!$G$11) -> 5040
B85: 3.027 | C85: Exterior Doors (Basic Steel) | D85: Insulated steel exterior doors: D1 entry (with 2 sidelights), D2 garage man door, garage-to-house door (self-closing, gas-proofed). | E85: 3 | F85: Each | G85: 1800 | H85: =E85*G85 -> 5400 | I85: =H85/(1-Summary!$G$11) -> 9000
B86: 3.028 | C86: Exterior Door Installation | D86: Exterior door installation. | E86: 3 | F86: Each | G86: 650 | H86: =E86*G86 -> 1950 | I86: =H86/(1-Summary!$G$11) -> 3250
B87: 3.029 | C87: Exterior Door Hardware | D87: Exterior door hardware (basic lever / entry handleset, deadbolt). | E87: 3 | F87: Each | G87: 350 | H87: =E87*G87 -> 1050 | I87: =H87/(1-Summary!$G$11) -> 1750
B88: 3.030 | C88: Garage Doors (standard size) | D88: D4 16'-0" x 8'-0" insulated steel garage door (opener not included). | E88: 1 | F88: Each | G88: 3500 | H88: =E88*G88 -> 3500 | I88: =H88/(1-Summary!$G$11) -> 5833.3333
C89: Subtotal — Windows & Exterior Doors | H89: =SUM(H83:H88) -> 32984 | I89: =SUM(I83:I88) -> 54973.333
B91: EXTERIOR CLADDING: BRICK, STONE & STUCCO
B92: 3.073 | C92: Exterior Masonry material | D92: Brick and stone veneer, main floor and 4 stone columns, incl. ties, precast sills, brick ledge (supply and install). | E92: 2200 | F92: Square Foot | G92: 45 | H92: =E92*G92 -> 99000 | I92: =H92/(1-Summary!$G$11) -> 165000
B93: 3.078 | C93: Stucco | D93: Stucco veneer w/ R5 rigid, 2nd floor and parapets (supply and install). | E93: 1850 | F93: Square Foot | G93: 28 | H93: =E93*G93 -> 51800 | I93: =H93/(1-Summary!$G$11) -> 86333.333
B94: 3.061 | C94: House Wrap | D94: Sheathing membrane (Tyvek) behind brick/stone veneer. | E94: 2200 | F94: Square Foot | G94: 3.5 | H94: =E94*G94 -> 7700 | I94: =H94/(1-Summary!$G$11) -> 12833.333
B95: 3.072 | C95: Exterior Caulking | D95: Exterior caulking at windows, doors and penetrations. | E95: 370 | F95: Linear Feet | G95: 12 | H95: =E95*G95 -> 4440 | I95: =H95/(1-Summary!$G$11) -> 7400
C96: Subtotal — Exterior Cladding: Brick, Stone & Stucco | H96: =SUM(H92:H95) -> 162940 | I96: =SUM(I92:I95) -> 271566.67
B98: PLUMBING ROUGH-IN
B99: 3.001 | C99: Plumbing - Underground | D99: Underground plumbing: basement drains, sump, floor drain, 3-pc rough-in drains, radon rough-in, laterals. | E99: 100 | F99: Linear Feet | G99: 85 | H99: =E99*G99 -> 8500 | I99: =H99/(1-Summary!$G$11) -> 14166.667
B100: 3.047 | C100: Rough-In Plumbing | D100: Plumbing rough-in: powder room, main bath, ensuite, kitchen, laundry, 2 hose bibs; basement 3-pc rough-in only. | E100: 1 | F100: Lump Sum | G100: 18000 | H100: =E100*G100 -> 18000 | I100: =H100/(1-Summary!$G$11) -> 30000
C101: Subtotal — Plumbing Rough-In | H101: =SUM(H99:H100) -> 26500 | I101: =SUM(I99:I100) -> 44166.667
B103: HVAC & GAS ROUGH-IN
B104: 3.048 | C104: Rough-In Gas & Venting | D104: Gas rough-in and venting: furnace, water heater, range. | E104: 1 | F104: Lump Sum | G104: 6500 | H104: =E104*G104 -> 6500 | I104: =H104/(1-Summary!$G$11) -> 10833.333
B105: 3.049 | C105: Rough-In HVAC | D105: HVAC: high-efficiency gas furnace, central A/C, HRV, ductwork and controls. | E105: 1 | F105: Lump Sum | G105: 22000 | H105: =E105*G105 -> 22000 | I105: =H105/(1-Summary!$G$11) -> 36666.667
C106: Subtotal — HVAC & Gas Rough-In | H106: =SUM(H104:H105) -> 28500 | I106: =SUM(I104:I105) -> 47500
B108: ELECTRICAL ROUGH-IN & SERVICE
B109: 3.046 | C109: Electrical - Underground | D109: Electrical underground service trench from street. | E109: 50 | F109: Linear Feet | G109: 65 | H109: =E109*G109 -> 3250 | I109: =H109/(1-Summary!$G$11) -> 5416.6667
B110: 3.050 | C110: Electrical Service (200 Amp if required) | D110: New 200 A electrical service and panel. | E110: 1 | F110: Lump Sum | G110: 8500 | H110: =E110*G110 -> 8500 | I110: =H110/(1-Summary!$G$11) -> 14166.667
B111: 3.051 | C111: Electrical Rough-In | D111: Electrical rough-in: devices, pot lights, smoke/CO, appliance circuits; basic code lighting/outlets in basement. | E111: 1 | F111: Lump Sum | G111: 18000 | H111: =E111*G111 -> 18000 | I111: =H111/(1-Summary!$G$11) -> 30000
B112: 3.042 | C112: Low voltage rough wire | D112: Low-voltage rough wire: data/coax to main locations. | E112: 200 | F112: Linear Feet | G112: 18 | H112: =E112*G112 -> 3600 | I112: =H112/(1-Summary!$G$11) -> 6000
C113: Subtotal — Electrical Rough-In & Service | H113: =SUM(H109:H112) -> 33350 | I113: =SUM(I109:I112) -> 55583.333
B115: INSULATION & AIR SEALING
B116: 3.054 | C116: Batt Insulation | D116: R22 batt + 6 mil poly at above-grade walls (3,060 SF) and full-height basement wall blanket (1,450 SF). | E116: 4510 | F116: Square Foot | G116: 2 | H116: =E116*G116 -> 9020 | I116: =H116/(1-Summary!$G$11) -> 15033.333
B117: 3.125 | C117: Insulation (Blown-in) | D117: Blown-in attic insulation to SB-12 value. | E117: 1470 | F117: Square Foot | G117: 2.25 | H117: =E117*G117 -> 3307.5 | I117: =H117/(1-Summary!$G$11) -> 5512.5
...

Sheet Turnkey Option
B1: TURNKEY OPTION — ENTRY-LEVEL FINISHES TO OCCUPANCY
B2: Not included in the price to drywall. Shown so the client can see the cost to finish with PalmView.
B4: OPTIONAL — COST TO FINISH WITH PALMVIEW (ENTRY LEVEL)
C5: Division | H5: Cost | I5: Price
C6: Mechanical & Electrical Finish | H6: ='Turnkey Option'!$H$28 -> 19000 | I6: ='Turnkey Option'!$I$28 -> 31666.667
C7: Prime & Finish Paint | H7: ='Turnkey Option'!$H$33 -> 14650 | I7: ='Turnkey Option'!$I$33 -> 24416.667
C8: Interior Doors, Trim & Hardware | H8: ='Turnkey Option'!$H$40 -> 35590 | I8: ='Turnkey Option'!$I$40 -> 59316.667
C9: Flooring & Tile | H9: ='Turnkey Option'!$H$50 -> 34354.5 | I9: ='Turnkey Option'!$I$50 -> 57257.5
C10: Stairs & Railings | H10: ='Turnkey Option'!$H$55 -> 9080 | I10: ='Turnkey Option'!$I$55 -> 15133.333
C11: Cabinets & Countertops | H11: ='Turnkey Option'!$H$62 -> 21375 | I11: ='Turnkey Option'!$I$62 -> 35625
C12: Fixtures, Lighting, Glass & Appliances | H12: ='Turnkey Option'!$H$73 -> 30330 | I12: ='Turnkey Option'!$I$73 -> 50550
C13: Exterior Railings, Steps, Driveway & Sod | H13: ='Turnkey Option'!$H$82 -> 25835 | I13: ='Turnkey Option'!$I$82 -> 43058.333
C14: Finishing Supervision, Inspections & Closeout | H14: ='Turnkey Option'!$H$96 -> 84650 | I14: ='Turnkey Option'!$I$96 -> 141083.33
C15: Total optional finishing | H15: =SUM(H6:H14) -> 274864.5 | I15: =SUM(I6:I14) -> 458107.5
C16: Price to drywall (from Summary) | H16: =Summary!D37 -> 1084498.7 | I16: =Summary!E37 -> 1759497.9
C17: TURNKEY TOTAL, ENTRY LEVEL (before HST) | H17: =H15+H16 -> 1359363.2 | I17: =I15+I16 -> 2217605.4
C18: Turnkey price per SF above grade | I18: =I17/Summary!$D$12 -> 756.8619
B22: Code | C22: Cost Item | D22: Scope Description | E22: Qty | F22: Unit | G22: Unit Cost | H22: Cost | I22: Price
B23: MECHANICAL & ELECTRICAL FINISH
B24: 3.037 | C24: Plumbing - Finish & Fixture Set | D24: Plumbing finish and fixture set (fixtures by allowance). | E24: 1 | F24: Lump Sum | G24: 4000 | H24: =E24*G24 -> 4000 | I24: =H24/(1-Summary!$G$11) -> 6666.6667
B25: 3.035 | C25: Gas - Finish & Appliance Connections | D25: Gas finish and appliance connections. | E25: 1 | F25: Lump Sum | G25: 2000 | H25: =E25*G25 -> 2000 | I25: =H25/(1-Summary!$G$11) -> 3333.3333
B26: 3.033 | C26: HVAC - Finish, Equipment Set & Startup | D26: HVAC finish, equipment set and startup. | E26: 1 | F26: Lump Sum | G26: 6000 | H26: =E26*G26 -> 6000 | I26: =H26/(1-Summary!$G$11) -> 10000
B27: 3.040 | C27: Electrical - Finish, Devices & Fixture Hookup | D27: Electrical finish, devices and fixture hookup (fixtures by allowance). | E27: 1 | F27: Lump Sum | G27: 7000 | H27: =E27*G27 -> 7000 | I27: =H27/(1-Summary!$G$11) -> 11666.667
C28: Subtotal — Mechanical & Electrical Finish | H28: =SUM(H24:H27) -> 19000 | I28: =SUM(I24:I27) -> 31666.667
B30: PRIME & FINISH PAINT
B31: 4.002 | C31: Interior Painting - Prime Coat | D31: Interior prime coat, main and 2nd floor. | E31: 2930 | F31: Square Foot | G31: 1.5 | H31: =E31*G31 -> 4395 | I31: =H31/(1-Summary!$G$11) -> 7325
B32: 4.070 | C32: Interior Painting - Finish Coats | D32: Interior finish paint, 2 coats, builder white, main and 2nd floor. | E32: 2930 | F32: Square Foot | G32: 3.5 | H32: =E32*G32 -> 10255 | I32: =H32/(1-Summary!$G$11) -> 17091.667
C33: Subtotal — Prime & Finish Paint | H33: =SUM(H31:H32) -> 14650 | I33: =SUM(I31:I32) -> 24416.667
B35: INTERIOR DOORS, TRIM & HARDWARE
B36: 4.004 | C36: Interior Doors | D36: Interior doors, hollow-core moulded slab, pre-hung, installed. | E36: 22 | F36: Each | G36: 650 | H36: =E36*G36 -> 14300 | I36: =H36/(1-Summary!$G$11) -> 23833.333
B37: 4.006 | C37: Interior Door Hardware | D37: Interior door hardware, entry-level levers. | E37: 22 | F37: Each | G37: 45 | H37: =E37*G37 -> 990 | I37: =H37/(1-Summary!$G$11) -> 1650
B38: 4.008 | C38: Molding Materials | D38: MDF baseboard and casing, paint grade. | E38: 2100 | F38: Linear Feet | G38: 4 | H38: =E38*G38 -> 8400 | I38: =H38/(1-Summary!$G$11) -> 14000
B39: 4.010 | C39: Finish Carpentry (Trim Moldings and doors labour) | D39: Finish carpentry labour, trim install. | E39: 140 | F39: Hours | G39: 85 | H39: =E39*G39 -> 11900 | I39: =H39/(1-Summary!$G$11) -> 19833.333
C40: Subtotal — Interior Doors, Trim & Hardware | H40: =SUM(H36:H39) -> 35590 | I40: =SUM(I36:I39) -> 59316.667
B42: FLOORING & TILE
B43: 4.052 | C43: Flooring Allowance (if applicable) | D43: Flooring allowance: vinyl plank / laminate, main and 2nd floor, supply and install. | E43: 2450 | F43: Square Foot | G43: 8 | H43: =E43*G43 -> 19600 | I43: =H43/(1-Summary!$G$11) -> 32666.667
B44: 4.053 | C44: Tile Allowance (if applicable) | D44: Tile supply allowance: bath/laundry/entry floors, shower and tub walls, backsplash. | E44: 505 | F44: Square Foot | G44: 6 | H44: =E44*G44 -> 3030 | I44: =H44/(1-Summary!$G$11) -> 5050
B45: 4.014 | C45: Tile Installation Labour (general floor & wall) | D45: Tile install labour, floors. | E45: 335 | F45: Square Foot | G45: 15 | H45: =E45*G45 -> 5025 | I45: =H45/(1-Summary!$G$11) -> 8375
B46: 4.013 | C46: Tile Setting Materials (thinset, membrane, backer) | D46: Tile setting materials, floors. | E46: 335 | F46: Square Foot | G46: 8.5 | H46: =E46*G46 -> 2847.5 | I46: =H46/(1-Summary!$G$11) -> 4745.8333
B47: 4.061 | C47: Tile Shower Wall - Install (labour + setting materials) | D47: Tile install, shower and tub walls (labour + setting materials). | E47: 140 | F47: Square Foot | G47: 18 | H47: =E47*G47 -> 2520 | I47: =H47/(1-Summary!$G$11) -> 4200
B48: 4.060 | C48: Tile Shower Floor - Install (labour + setting materials) | D48: Tile install, ensuite shower floor. | E48: 16 | F48: Square Foot | G48: 12 | H48: =E48*G48 -> 192 | I48: =H48/(1-Summary!$G$11) -> 320
B49: 4.062 | C49: Tile Backsplash - Install (labour + setting materials) | D49: Tile install, kitchen backsplash. | E49: 30 | F49: Square Foot | G49: 38 | H49: =E49*G49 -> 1140 | I49: =H49/(1-Summary!$G$11) -> 1900
C50: Subtotal — Flooring & Tile | H50: =SUM(H43:H49) -> 34354.5 | I50: =SUM(I43:I49) -> 57257.5
B52: STAIRS & RAILINGS
B53: 4.030 | C53: Custom Stairs | D53: Main-to-2nd floor stair finish (basement stair left as framed). | E53: 1 | F53: Lump Sum | G53: 5000 | H53: =E53*G53 -> 5000 | I53: =H53/(1-Summary!$G$11) -> 8333.3333
B54: 4.029 | C54: Interior Railing | D54: Interior railing, stair and 2nd floor landing, entry-level oak/picket. | E54: 34 | F54: Linear Feet | G54: 120 | H54: =E54*G54 -> 4080 | I54: =H54/(1-Summary!$G$11) -> 6800
C55: Subtotal — Stairs & Railings | H55: =SUM(H53:H54) -> 9080 | I55: =SUM(I53:I54) -> 15133.333
B57: CABINETS & COUNTERTOPS
B58: 4.032 | C58: Cabinets - Pre-manufactured | D58: Pre-manufactured cabinets: kitchen, island, pantry, laundry. | E58: 40 | F58: Linear Feet | G58: 280 | H58: =E58*G58 -> 11200 | I58: =H58/(1-Summary!$G$11) -> 18666.667
B59: 4.034 | C59: Cabinet install | D59: Cabinet install. | E59: 40 | F59: Linear Feet | G59: 85 | H59: =E59*G59 -> 3400 | I59: =H59/(1-Summary!$G$11) -> 5666.6667
B60: 4.054 | C60: Cabinet Hardware Allowance (if applicable) | D60: Cabinet hardware allowance. | E60: 1 | F60: Lump Sum | G60: 600 | H60: =E60*G60 -> 600 | I60: =H60/(1-Summary!$G$11) -> 1000
B61: 4.035 | C61: Countertops | D61: Countertops, entry-level quartz/laminate, kitchen and island. | E61: 95 | F61: Square Foot | G61: 65 | H61: =E61*G61 -> 6175 | I61: =H61/(1-Summary!$G$11) -> 10291.667
C62: Subtotal — Cabinets & Countertops | H62: =SUM(H58:H61) -> 21375 | I62: =SUM(I58:I61) -> 35625
B64: FIXTURES, LIGHTING, GLASS & APPLIANCES
B65: 4.064 | C65: Bath Vanities | D65: Bath vanities with tops: powder, main bath, ensuite. | E65: 3 | F65: Each | G65: 1200 | H65: =E65*G65 -> 3600 | I65: =H65/(1-Summary!$G$11) -> 6000
B66: 4.050 | C66: Plumbing Fixture Allowance | D66: Plumbing fixture allowance (3 toilets, faucets, tub, freestanding tub, shower valve, kitchen sink, laundry tub). | E66: 1 | F66: Lump Sum | G66: 9000 | H66: =E66*G66 -> 9000 | I66: =H66/(1-Summary!$G$11) -> 15000
B67: 4.051 | C67: Lighting Fixture Allowance | D67: Interior lighting fixture allowance. | E67: 1 | F67: Lump Sum | G67: 4500 | H67: =E67*G67 -> 4500 | I67: =H67/(1-Summary!$G$11) -> 7500
B68: 3.091 | C68: Exterior Lighting | D68: Exterior light fixture allowance. | E68: 6 | F68: Each | G68: 150 | H68: =E68*G68 -> 900 | I68: =H68/(1-Summary!$G$11) -> 1500
B69: 4.058 | C69: Shower Glass | D69: Ensuite shower glass. | E69: 1 | F69: Each | G69: 1500 | H69: =E69*G69 -> 1500 | I69: =H69/(1-Summary!$G$11) -> 2500
B70: 4.069 | C70: Mirrors | D70: Bathroom mirrors. | E70: 3 | F70: Each | G70: 250 | H70: =E70*G70 -> 750 | I70: =H70/(1-Summary!$G$11) -> 1250
B71: 4.040 | C71: Hardware & Accessories fixtures | D71: Bath accessories (towel bars, TP holders). | E71: 9 | F71: Each | G71: 120 | H71: =E71*G71 -> 1080 | I71: =H71/(1-Summary!$G$11) -> 1800
B72: 4.037 | C72: Appliance Package | D72: Appliance package allowance, entry level (fridge, range, DW, hood, W/D). | E72: 1 | F72: Lump Sum | G72: 9000 | H72: =E72*G72 -> 9000 | I72: =H72/(1-Summary!$G$11) -> 15000
C73: Subtotal — Fixtures, Lighting, Glass & Appliances | H73: =SUM(H65:H72) -> 30330 | I73: =SUM(I65:I72) -> 50550
B75: EXTERIOR RAILINGS, STEPS, DRIVEWAY & SOD
B76: 3.092 | C76: Exterior Railing | D76: Exterior aluminum vista railing at raised patio and front steps. | E76: 37 | F76: Linear Feet | G76: 85 | H76: =E76*G76 -> 3145 | I76: =H76/(1-Summary!$G$11) -> 5241.6667
B77: 3.108 | C77: Masonry Supply | D77: Precast steps, front porch and rear patio (supply). | E77: 40 | F77: Square Foot | G77: 65 | H77: =E77*G77 -> 2600 | I77: =H77/(1-Summary!$G$11) -> 4333.3333
B78: 3.109 | C78: Masonry Labour | D78: Precast steps, install. | E78: 40 | F78: Square Foot | G78: 45 | H78: =E78*G78 -> 1800 | I78: =H78/(1-Summary!$G$11) -> 3000
B79: 3.110 | C79: Asphalt areas | D79: New asphalt driveway (approx. 24'-6" x 36'). | E79: 880 | F79: Square Foot | G79: 8 | H79: =E79*G79 -> 7040 | I79: =H79/(1-Summary!$G$11) -> 11733.333
B80: 3.120 | C80: Grass roll Supply | D80: Sod supply, disturbed areas. | E80: 5000 | F80: Square Foot | G80: 1.25 | H80: =E80*G80 -> 6250 | I80: =H80/(1-Summary!$G$11) -> 10416.667
B81: 3.121 | C81: Grass roll Labour | D81: Sod install. | E81: 5000 | F81: Square Foot | G81: 1 | H81: =E81*G81 -> 5000 | I81: =H81/(1-Summary!$G$11) -> 8333.3333
C82: Subtotal — Exterior Railings, Steps, Driveway & Sod | H82: =SUM(H76:H81) -> 25835 | I82: =SUM(I76:I81) -> 43058.333
B84: FINISHING SUPERVISION, INSPECTIONS & CLOSEOUT
B85: 1.040 | C85: Site Supervision & Project Management (Blended Monthly) | D85: Site supervision and PM, finishing phase, 3 additional months. | E85: 3 | F85: Months | G85: 12000 | H85: =E85*G85 -> 36000 | I85: =H85/(1-Summary!$G$11) -> 60000
B86: 1.051 | C86: Waste Disposal / Garbage Bins | D86: Waste bins, finishing phase. | E86: 2 | F86: Months | G86: 1800 | H86: =E86*G86 -> 3600 | I86: =H86/(1-Summary!$G$11) -> 6000
B87: 5.005 | C87: Final Grade | D87: Final grading and lot grading certificate. | E87: 2500 | F87: Square Foot | G87: 4.5 | H87: =E87*G87 -> 11250 | I87: =H87/(1-Summary!$G$11) -> 18750
B88: 3.060 | C88: Final Air test | D88: Final air test. | E88: 1 | F88: Lump Sum | G88: 1800 | H88: =E88*G88 -> 1800 | I88: =H88/(1-Summary!$G$11) -> 3000
B89: 5.006 | C89: HVAC Balancing | D89: HVAC balancing. | E89: 1 | F89: Lump Sum | G89: 1800 | H89: =E89*G89 -> 1800 | I89: =H89/(1-Summary!$G$11) -> 3000
B90: 5.007 | C90: Electrical Inspection (ESA) | D90: ESA final inspection. | E90: 1 | F90: Lump Sum | G90: 1200 | H90: =E90*G90 -> 1200 | I90: =H90/(1-Summary!$G$11) -> 2000
B91: 5.008 | C91: Final Building Inspections | D91: Final building inspections. | E91: 1 | F91: Lump Sum | G91: 2500 | H91: =E91*G91 -> 2500 | I91: =H91/(1-Summary!$G$11) -> 4166.6667
B92: 5.009 | C92: Occupancy Requirements | D92: Occupancy requirements. | E92: 1 | F92: Lump Sum | G92: 1500 | H92: =E92*G92 -> 1500 | I92: =H92/(1-Summary!$G$11) -> 2500
B93: 5.010 | C93: Professional Final Cleaning | D93: Professional final cleaning. | E93: 1 | F93: Lump Sum | G93: 4500 | H93: =E93*G93 -> 4500 | I93: =H93/(1-Summary!$G$11) -> 7500
B94: 5.012 | C94: Deficiency Completion / Touch-Ups | D94: Deficiency completion and touch-ups. | E94: 1 | F94: Lump Sum | G94: 8500 | H94: =E94*G94 -> 8500 | I94: =H94/(1-Summary!$G$11) -> 14166.667
B95: 5.014 | C95: Warranty Service Allowance | D95: Warranty service reserve. | E95: 1 | F95: Lump Sum | G95: 12000 | H95: =E95*G95 -> 12000 | I95: =H95/(1-Summary!$G$11) -> 20000
C96: Subtotal — Finishing Supervision, Inspections & Closeout | H96: =SUM(H85:H95) -> 84650 | I96: =SUM(I85:I95) -> 141083.33

Sheet Schedule
B1: APPROXIMATE SCHEDULE
B2: Week 1 = construction start after permit. Change the yellow start date and every date updates.
B4: Construction start (Week 1, Monday) | E4: 46398
I5: =TEXT($E$4+(I6-1)*7,"mmm d") -> Nov 16 | M5: =TEXT($E$4+(M6-1)*7,"mmm d") -> Dec 14 | Q5: =TEXT($E$4+(Q6-1)*7,"mmm d") -> Jan 11 | U5: =TEXT($E$4+(U6-1)*7,"mmm d") -> Feb 8 | Y5: =TEXT($E$4+(Y6-1)*7,"mmm d") -> Mar 8 | AC5: =TEXT($E$4+(AC6-1)*7,"mmm d") -> Apr 5 | AG5: =TEXT($E$4+(AG6-1)*7,"mmm d") -> May 3 | AK5: =TEXT($E$4+(AK6-1)*7,"mmm d") -> May 31 | AO5: =TEXT($E$4+(AO6-1)*7,"mmm d") -> Jun 28 | AS5: =TEXT($E$4+(AS6-1)*7,"mmm d") -> Jul 26 | AW5: =TEXT($E$4+(AW6-1)*7,"mmm d") -> Aug 23 | BA5: =TEXT($E$4+(BA6-1)*7,"mmm d") -> Sep 20
B6: Phase | C6: Trade | D6: Start Wk | E6: Weeks | F6: End Wk | G6: Start | H6: Finish | I6: -7 | J6: -6 | K6: -5 | L6: -4 | M6: -3 | N6: -2 | O6: -1 | P6: 0 | Q6: 1 | R6: 2 | S6: 3 | T6: 4 | U6: 5 | V6: 6 | W6: 7 | X6: 8 | Y6: 9 | Z6: 10 | AA6: 11 | AB6: 12 | AC6: 13 | AD6: 14 | AE6: 15 | AF6: 16 | AG6: 17 | AH6: 18 | AI6: 19 | AJ6: 20 | AK6: 21 | AL6: 22 | AM6: 23 | AN6: 24 | AO6: 25 | AP6: 26 | AQ6: 27 | AR6: 28 | AS6: 29 | AT6: 30 | AU6: 31 | AV6: 32 | AW6: 33 | AX6: 34 | AY6: 35 | AZ6: 36 | BA6: 37 | BB6: 38 | BC6: 39
B7: PRE-CONSTRUCTION
B8: Permit issuance, utility disconnects, hazardous survey | C8: Owner / PalmView | D8: -7 | E8: 8 | F8: =D8+E8-1 -> 0 | G8: =$E$4+(D8-1)*7 -> 46342 | H8: =$E$4+(F8-1)*7+4 -> 46395
B9: FIXED SCOPE — TO DRYWALL
B10: Site setup, fencing, tree protection | C10: PalmView | D10: 1 | E10: 1 | F10: =D10+E10-1 -> 1 | G10: =$E$4+(D10-1)*7 -> 46398 | H10: =$E$4+(F10-1)*7+4 -> 46402
B11: Abatement (if required) | C11: Abatement | D11: 1 | E11: 1 | F11: =D11+E11-1 -> 1 | G11: =$E$4+(D11-1)*7 -> 46398 | H11: =$E$4+(F11-1)*7+4 -> 46402
B12: Demolition & site clearing | C12: Demolition | D12: 2 | E12: 2 | F12: =D12+E12-1 -> 3 | G12: =$E$4+(D12-1)*7 -> 46405 | H12: =$E$4+(F12-1)*7+4 -> 46416
B13: Stakeout & excavation | C13: Survey / Excavation | D13: 4 | E13: 1 | F13: =D13+E13-1 -> 4 | G13: =$E$4+(D13-1)*7 -> 46419 | H13: =$E$4+(F13-1)*7+4 -> 46423
B14: Footings | C14: Forming | D14: 5 | E14: 1 | F14: =D14+E14-1 -> 5 | G14: =$E$4+(D14-1)*7 -> 46426 | H14: =$E$4+(F14-1)*7+4 -> 46430
B15: Foundation walls | C15: Forming | D15: 6 | E15: 2 | F15: =D15+E15-1 -> 7 | G15: =$E$4+(D15-1)*7 -> 46433 | H15: =$E$4+(F15-1)*7+4 -> 46444
B16: Dampproofing, weeping tile, underground services | C16: Waterproof / Plumber | D16: 8 | E16: 1 | F16: =D16+E16-1 -> 8 | G16: =$E$4+(D16-1)*7 -> 46447 | H16: =$E$4+(F16-1)*7+4 -> 46451
B17: Backfill & rough grade | C17: Excavation | D17: 9 | E17: 1 | F17: =D17+E17-1 -> 9 | G17: =$E$4+(D17-1)*7 -> 46454 | H17: =$E$4+(F17-1)*7+4 -> 46458
B18: Framing & structural steel | C18: Framer / Steel | D18: 10 | E18: 5 | F18: =D18+E18-1 -> 14 | G18: =$E$4+(D18-1)*7 -> 46461 | H18: =$E$4+(F18-1)*7+4 -> 46493
B19: Roof trusses (crane) & sheathing | C19: Framer | D19: 14 | E19: 1 | F19: =D19+E19-1 -> 14 | G19: =$E$4+(D19-1)*7 -> 46489 | H19: =$E$4+(F19-1)*7+4 -> 46493
B20: Roofing: shingles & flat roofs | C20: Roofer | D20: 15 | E20: 2 | F20: =D20+E20-1 -> 16 | G20: =$E$4+(D20-1)*7 -> 46496 | H20: =$E$4+(F20-1)*7+4 -> 46507
B21: Windows & exterior doors | C21: Windows | D21: 15 | E21: 2 | F21: =D21+E21-1 -> 16 | G21: =$E$4+(D21-1)*7 -> 46496 | H21: =$E$4+(F21-1)*7+4 -> 46507
... B29: Drywall complete — fixed scope handover | C29: PalmView | D29: 27 | E29: 1 | F29: =D29+E29-1 -> 27 | G29: =$E$4+(D29-1)*7 -> 46580 | H29: =$E$4+(F29-1)*7+4 -> 46584
B30: OPTIONAL — FINISH TO OCCUPANCY
B31: Prime, trim, doors, stairs & railings | C31: Finish carpentry | D31: 28 | E31: 3 | F31: =D31+E31-1 -> 30 | G31: =$E$4+(D31-1)*7 -> 46587 | H31: =$E$4+(F31-1)*7+4 -> 46605
B32: Cabinets & countertops | C32: Cabinets / Counters | D32: 28 | E32: 4 | F32: =D32+E32-1 -> 31 | G32: =$E$4+(D32-1)*7 -> 46587 | H32: =$E$4+(F32-1)*7+4 -> 46612
B33: Flooring & tile | C33: Flooring / Tile | D33: 30 | E33: 4 | F33: =D33+E33-1 -> 33 | G33: =$E$4+(D33-1)*7 -> 46601 | H33: =$E$4+(F33-1)*7+4 -> 46626
B34: Finish paint | C34: Painter | D34: 33 | E34: 2 | F34: =D34+E34-1 -> 34 | G34: =$E$4+(D34-1)*7 -> 46622 | H34: =$E$4+(F34-1)*7+4 -> 46633
B35: Mechanical & electrical finish, fixtures | C35: Mech / Elec | D35: 34 | E35: 2 | F35: =D35+E35-1 -> 35 | G35: =$E$4+(D35-1)*7 -> 46629 | H35: =$E$4+(F35-1)*7+4 -> 46640
B36: Final grade, driveway, sod | C36: Landscape / Paving | D36: 34 | E36: 3 | F36: =D36+E36-1 -> 36 | G36: =$E$4+(D36-1)*7 -> 46629 | H36: =$E$4+(F36-1)*7+4 -> 46647
B37: Final clean, inspections, occupancy | C37: PalmView / City | D37: 37 | E37: 2 | F37: =D37+E37-1 -> 38 | G37: =$E$4+(D37-1)*7 -> 46650 | H37: =$E$4+(F37-1)*7+4 -> 46661
B38: Deficiencies & handover | C38: PalmView | D38: 39 | E38: 1 | F38: =D38+E38-1 -> 39 | G38: =$E$4+(D38-1)*7 -> 46664 | H38: =$E$4+(F38-1)*7+4 -> 46668
B40: KEY DATES
B41: Construction start | G41: =E4 -> 46398
B42: Foundation complete | G42: =$E$4+8*7+4 -> 46458
B43: Closed in: framed, roofed, windows | G43: =$E$4+15*7+4 -> 46507
B44: DRYWALL COMPLETE — FIXED SCOPE DONE (~6 months) | G44: =$E$4+26*7+4 -> 46584
B45: Occupancy, if finishing is added (~9 months) | G45: =$E$4+38*7+4 -> 46668
